{
  "aida_page": "4543",
  "cid": "JORFTEXT000018622600",
  "classements": [
    {
      "alinea": null,
      "regime": "A",
      "rubrique": "2130",
      "state": "ACTIVE"
    }
  ],
  "date_of_signature": "2008-04-01",
  "is_transverse": false,
  "nickname": null,
  "nor": "DEVP0802292A",
  "reason_deleted": null,
  "source": "LEGIFRANCE",
  "state": "VIGUEUR",
  "title": " Arr\u00eat\u00e9 du 01/04/08 fixant les r\u00e8gles techniques auxquelles doivent satisfaire les piscicultures d'eau douce soumises \u00e0 autorisation au titre du livre V du code de l'environnement (rubrique 2130 de la nomenclature des installations class\u00e9es) "
}